{
	"info": {
		"_postman_id": "e6e104e9-62ff-470c-830f-e34259022823",
		"name": "API-Backend - CRUD",
		"description": "### 1\\. Rota para Criar Novos Produtos\n\n#### URL:\n\n`POST http://localhost:8000/api/produtos`\n\n#### Método HTTP:\n\n`POST`\n\n#### Authorization:\n\n`Bearer Token`\n\n#### Exemplo de solicitação:\n\n``` json\n{\n    \"name\": \"caixa_de_som\",\n    \"description\": \"Caixa de som\",\n    \"price\": \"550.00\",\n    \"status\": \"em estoque\",\n    \"stock_quantity\": 10\n}\n\n ```\n\n#### Exemplo de sucesso:\n\n``` json\n{\n    \"message\": \"Produto Criado!\",\n    \"produto\": {\n        \"name\": \"caixa_de_som\",\n        \"description\": \"Caixa de som\",\n        \"price\": \"550.00\",\n        \"status\": \"em estoque\",\n        \"stock_quantity\": 10,\n        \"updated_at\": \"2024-05-14T01:24:07.000000Z\",\n        \"created_at\": \"2024-05-14T01:24:07.000000Z\",\n        \"id\": 21\n    }\n}\n\n ```\n\n### 2\\. Rota para Listar Todos os Produtos\n\n#### URL:\n\n`GET http://localhost:8000/api/produtos`\n\n#### Método HTTP:\n\n`GET`\n\n#### Authorization:\n\n`Bearer Token`\n\n#### Exemplo de solicitação:\n\n``` json\n{\n        \"id\": 1,\n        \"name\": \"molestiae\",\n        \"description\": \"Quas dolores laudantium et id iusto fugit et.\",\n        \"price\": \"716.19\"\n    },\n    {\n        \"id\": 2,\n        \"name\": \"incidunt\",\n        \"description\": \"Illo iusto commodi illum id et.\",\n        \"price\": \"829.62\"\n    }\n}\n\n ```\n\n### 3\\. Rota para Editar um Produto Existente\n\n#### URL:\n\n`PUT http://localhost:8000/api/produtos/{id}`\n\n#### Método HTTP:\n\n`PUT`\n\n#### Authorization:\n\n`Bearer Token`\n\n#### Parâmetros:\n\n- `{id}`: ID do produto a ser atualizado (parâmetro de rota).\n    \n\n#### Exemplo de solicitação:\n\n``` json\n{\n    \"name\": \"caixa_de_som_jbl\",\n    \"description\": \"Caixa de som JBL\",\n    \"price\": \"585.00\",\n    \"status\": \"em estoque\",\n    \"stock_quantity\": 10\n}\n\n ```\n\n#### Exemplo de Sucesso:\n\n``` json\n{\n    \"message\": \"Produto Atualizado!\",\n    \"produto\": {\n        \"id\": 7,\n        \"name\": \"caixa_de_som_jbl\",\n        \"description\": \"Caixa de som JBL\",\n        \"price\": \"585.00\",\n        \"status\": \"em estoque\",\n        \"stock_quantity\": 10,\n        \"created_at\": \"2024-05-14T01:07:48.000000Z\",\n        \"updated_at\": \"2024-05-14T01:26:23.000000Z\"\n    }\n}\n\n ```\n\n#### Exemplo de erro:\n\n``` json\n{\n    \"message\": \"Produto Inexistente!\"\n}\n\n ```\n\n### 4\\. Rota para Excluir um Produto\n\n#### URL:\n\n`DELETE http://localhost:8000/api/produtos/{id}`\n\n#### Método HTTP:\n\n`DELETE`\n\n#### Authorization:\n\n`Bearer Token`\n\n#### Parâmetros:\n\n- `{id}`: ID do produto a ser excluído (parâmetro de rota).\n    \n\n#### Exemplo de sucesso:\n\n``` json\n{\n    \"message\": \"Produto Excluído!\"\n}\n\n ```\n\nExemplo de erro:\n\n``` json\n{\n    \"message\": \"Produto Inexistente!\"\n}\n\n ```\n\n### 5\\. Rota para Realizar Login\n\n#### URL:\n\n`POST http://localhost:8000/api/login`\n\n#### Método HTTP:\n\n`POST`\n\n#### Exemplo de solicitação:\n\n``` json\n{\n    \"email\": \"ycormier@example.net\",\n    \"password\": \"password\"\n}\n\n ```\n\n#### Exemplo de sucesso:\n\n``` json\n{\n    \"message\": \"Autorizado!\",\n    \"status\": 200,\n    \"token\": \"15|JfkwDTs65A9vJuSlgynXUDhrPFUi7Mt1nHlG9Pxy00aaea16\"\n}\n\n ```\n\n#### Exemplo de erro:\n\n``` json\n{\n    \"message\": \"Não autorizado!\",\n    \"status\": 403\n}\n\n ```",
		"schema": "https://schema.getpostman.com/json/collection/v2.1.0/collection.json",
		"_exporter_id": "28957516"
	},
	"item": [
		{
			"name": "Gravar",
			"protocolProfileBehavior": {
				"disabledSystemHeaders": {
					"accept": true
				}
			},
			"request": {
				"auth": {
					"type": "bearer",
					"bearer": [
						{
							"key": "token",
							"value": "15|JfkwDTs65A9vJuSlgynXUDhrPFUi7Mt1nHlG9Pxy00aaea16",
							"type": "string"
						}
					]
				},
				"method": "POST",
				"header": [
					{
						"key": "Accept",
						"value": "application/json"
					}
				],
				"body": {
					"mode": "raw",
					"raw": "{\r\n    \"name\": \"caixa_de_som\",\r\n    \"description\": \"Caixa de som\",\r\n    \"price\": \"550.00\",\r\n    \"status\": \"em estoque\",\r\n    \"stock_quantity\": 10\r\n}",
					"options": {
						"raw": {
							"language": "json"
						}
					}
				},
				"url": {
					"raw": "http://localhost:8000/api/produtos",
					"protocol": "http",
					"host": [
						"localhost"
					],
					"port": "8000",
					"path": [
						"api",
						"produtos"
					]
				}
			},
			"response": []
		},
		{
			"name": "Listar",
			"protocolProfileBehavior": {
				"disabledSystemHeaders": {
					"accept": true
				}
			},
			"request": {
				"auth": {
					"type": "bearer",
					"bearer": [
						{
							"key": "token",
							"value": "15|JfkwDTs65A9vJuSlgynXUDhrPFUi7Mt1nHlG9Pxy00aaea16",
							"type": "string"
						}
					]
				},
				"method": "GET",
				"header": [
					{
						"key": "Accept",
						"value": "application/json"
					},
					{
						"key": "Authorization",
						"value": "be"
					}
				],
				"url": {
					"raw": "http://localhost:8000/api/produtos",
					"protocol": "http",
					"host": [
						"localhost"
					],
					"port": "8000",
					"path": [
						"api",
						"produtos"
					]
				}
			},
			"response": []
		},
		{
			"name": "Editar",
			"protocolProfileBehavior": {
				"disabledSystemHeaders": {
					"accept": true
				}
			},
			"request": {
				"auth": {
					"type": "bearer",
					"bearer": [
						{
							"key": "token",
							"value": "15|JfkwDTs65A9vJuSlgynXUDhrPFUi7Mt1nHlG9Pxy00aaea16",
							"type": "string"
						}
					]
				},
				"method": "PUT",
				"header": [
					{
						"key": "Accept",
						"value": "application/json"
					}
				],
				"body": {
					"mode": "raw",
					"raw": "{\r\n    \"name\": \"caixa_de_som_jbl\",\r\n    \"description\": \"Caixa de som JBL\",\r\n    \"price\": \"585.00\",\r\n    \"status\": \"em estoque\",\r\n    \"stock_quantity\": 10\r\n}",
					"options": {
						"raw": {
							"language": "json"
						}
					}
				},
				"url": {
					"raw": "http://localhost:8000/api/produtos/7",
					"protocol": "http",
					"host": [
						"localhost"
					],
					"port": "8000",
					"path": [
						"api",
						"produtos",
						"7"
					]
				}
			},
			"response": []
		},
		{
			"name": "Excluir",
			"protocolProfileBehavior": {
				"disabledSystemHeaders": {
					"accept": true
				}
			},
			"request": {
				"auth": {
					"type": "bearer",
					"bearer": [
						{
							"key": "token",
							"value": "15|JfkwDTs65A9vJuSlgynXUDhrPFUi7Mt1nHlG9Pxy00aaea16",
							"type": "string"
						}
					]
				},
				"method": "DELETE",
				"header": [
					{
						"key": "Accept",
						"value": "application/json"
					}
				],
				"url": {
					"raw": "http://localhost:8000/api/produtos/7",
					"protocol": "http",
					"host": [
						"localhost"
					],
					"port": "8000",
					"path": [
						"api",
						"produtos",
						"7"
					]
				}
			},
			"response": []
		},
		{
			"name": "Login",
			"request": {
				"auth": {
					"type": "noauth"
				},
				"method": "POST",
				"header": [],
				"body": {
					"mode": "raw",
					"raw": "{\r\n    \"email\": \"ycormier@example.net\",\r\n    \"password\": \"password\"\r\n}",
					"options": {
						"raw": {
							"language": "json"
						}
					}
				},
				"url": {
					"raw": "http://localhost:8000/api/login",
					"protocol": "http",
					"host": [
						"localhost"
					],
					"port": "8000",
					"path": [
						"api",
						"login"
					],
					"query": [
						{
							"key": "email",
							"value": "pedro.belato@gmail.com",
							"disabled": true
						},
						{
							"key": "password",
							"value": "123456",
							"disabled": true
						}
					]
				}
			},
			"response": []
		}
	]
}